waveformtools/BMS.py
waveformtools/CoM.py
waveformtools/__init__.py
waveformtools/compare.py
waveformtools/config.py
waveformtools/dataIO.py
waveformtools/dataIO.py.bak
waveformtools/diagnostics.py
waveformtools/differentiate.py
waveformtools/extrapolate.py
waveformtools/extrapolate.py.ak
waveformtools/grids.py
waveformtools/integrate.py
waveformtools/legacy.py
waveformtools/modes_array.py
waveformtools/rotations.py
waveformtools/simulations.py
waveformtools/single_mode.py
waveformtools/spherical.py
waveformtools/spherical_array.py
waveformtools/transforms.py
waveformtools/waveforms.py
waveformtools/waveforms.py.bak
waveformtools/waveformtools.py
waveformtools/models/bilby.py
waveformtools/models/eob.py
waveformtools/models/imr.py
waveformtools/models/lal.py
waveformtools/models/utils.py
waveformtools/models/waveform_models.py
waveformtools/sxs/discover_sims.py
waveformtools/sxs/prepare_waveforms.py
waveformtools/sxs/run_prepare_waveforms.py
waveformtools-2025.8.26.dist-info/METADATA
waveformtools-2025.8.26.dist-info/WHEEL
waveformtools-2025.8.26.dist-info/licenses/LICENSE
waveformtools-2025.8.26.dist-info/RECORD
