Metadata-Version: 2.4
Name: waveformtools
Version: 2025.8.26
Summary:  Tools for working with numerical relativity and waveforms data 
Project-URL: Homepage, https://gitlab.com/vaishakp/waveformtools
Project-URL: Bug Tracker, https://gitlab.com/vaishakp/waveformtools/issues
Author-email: Vaishak Prasad <vaishakprasad@gmail.com>
License-File: LICENSE
Classifier: License :: OSI Approved :: MIT License
Classifier: Operating System :: OS Independent
Classifier: Programming Language :: Python :: 3
Requires-Python: >=3.11
Requires-Dist: datetime
Requires-Dist: h5py
Requires-Dist: matplotlib
Requires-Dist: numba
Requires-Dist: numpy
Requires-Dist: numpydoc
Requires-Dist: recommonmark
Requires-Dist: scipy
Requires-Dist: spectools
Requires-Dist: sphinx-rtd-theme
Requires-Dist: sympy
Requires-Dist: termcolor
Requires-Dist: vlconf
Provides-Extra: opt
Requires-Dist: gmpy; extra == 'opt'
Requires-Dist: gmpy2; extra == 'opt'
Requires-Dist: lalsuite; extra == 'opt'
Requires-Dist: ligo-common; extra == 'opt'
Requires-Dist: pycbc; extra == 'opt'
Requires-Dist: pyseobnr; extra == 'opt'
